zerotier/EnumUserAuth.py
zerotier/Error.py
zerotier/Network.py
zerotier/NetworkConfig.py
zerotier/NetworkDeleteStatus.py
zerotier/NetworkIpAssignmentPool.py
zerotier/NetworkMember.py
zerotier/NetworkMemberConfig.py
zerotier/NetworkRelay.py
zerotier/NetworkRule.py
zerotier/SystemStatus.py
zerotier/User.py
zerotier/__init__.py
zerotier/client.py
zerotier/client_support.py
zerotier/client_utils.py
zerotier/network_service.py
zerotier/self_service.py
zerotier/status_service.py
zerotier/user_service.py
zerotier-1.0.1.dist-info/DESCRIPTION.rst
zerotier-1.0.1.dist-info/METADATA
zerotier-1.0.1.dist-info/RECORD
zerotier-1.0.1.dist-info/WHEEL
zerotier-1.0.1.dist-info/metadata.json
zerotier-1.0.1.dist-info/top_level.txt
