Metadata-Version: 2.0
Name: zerotier
Version: 1.0.1
Summary: Zerotier API client
Home-page: https://github.com/g8os/zerotier_client
Author: Christophe de Carvalho
Author-email: christophe@gig.tech
License: Apache 2.0
Platform: UNKNOWN
Requires-Dist: requests (>=2.13.0)
Requires-Dist: python-dateutil (>=2.6.0)
